rgx/__init__.py
rgx/entities.py
rgx/meta.py
rgx/unicode_meta.py
rgx-2.0.0.dist-info/LICENSE
rgx-2.0.0.dist-info/METADATA
rgx-2.0.0.dist-info/WHEEL
rgx-2.0.0.dist-info/RECORD
