Metadata-Version: 2.1
Name: rgx
Version: 2.0.0
Summary: Typed, simple and readable regexp generation
Home-page: https://github.com/evtn/rgx
License: MIT
Keywords: regex,regexp,regular expressions
Author: Dmitry Gritsenko
Author-email: rgx@evtn.ru
Requires-Python: >=3.7,<4.0
Classifier: License :: OSI Approved :: MIT License
Classifier: Programming Language :: Python :: 3
Classifier: Programming Language :: Python :: 3.7
Classifier: Programming Language :: Python :: 3.8
Classifier: Programming Language :: Python :: 3.9
Classifier: Programming Language :: Python :: 3.10
Classifier: Programming Language :: Python :: 3.11
Classifier: Programming Language :: Python :: 3.12
Requires-Dist: wordstreamer (>=0.1.3,<0.2.0)
Project-URL: Repository, https://github.com/evtn/rgx
